mlx_weightlifter/__init__.py
mlx_weightlifter/config.py
mlx_weightlifter/dtypes.py
mlx_weightlifter/gguf.py
mlx_weightlifter/infer_checkpoint.py
mlx_weightlifter/infer_safetensors.py
mlx_weightlifter/neural_weights.py
mlx_weightlifter/pytorch.py
mlx_weightlifter/safetensors.py
mlx_weightlifter/weights.py
mlx_weightlifter-0.1.1.dist-info/licenses/LICENSE
mlx_weightlifter-0.1.1.dist-info/METADATA
mlx_weightlifter-0.1.1.dist-info/WHEEL
mlx_weightlifter-0.1.1.dist-info/top_level.txt
mlx_weightlifter-0.1.1.dist-info/RECORD
