Metadata-Version: 2.4
Name: mlx-weightlifter
Version: 0.1.1
Summary: Lift any checkpoint into MLX - PyTorch, Safetensors, GGUF
Author: Sydney Renee
License-Expression: MIT
Project-URL: Homepage, https://github.com/MLXPorts/mlx-weightlifter
Project-URL: Repository, https://github.com/MLXPorts/mlx-weightlifter
Project-URL: Issues, https://github.com/MLXPorts/mlx-weightlifter/issues
Keywords: mlx,apple,silicon,weights,checkpoints,gguf,safetensors,pytorch,weightlifter
Classifier: Development Status :: 4 - Beta
Classifier: Intended Audience :: Developers
Classifier: Intended Audience :: Science/Research
Classifier: Operating System :: MacOS :: MacOS X
Classifier: Programming Language :: Python :: 3
Classifier: Programming Language :: Python :: 3.10
Classifier: Programming Language :: Python :: 3.11
Classifier: Programming Language :: Python :: 3.12
Classifier: Topic :: Scientific/Engineering :: Artificial Intelligence
Requires-Python: >=3.10
License-File: LICENSE
Requires-Dist: mlx>=0.10.0
Provides-Extra: mlx-lm
Requires-Dist: mlx-lm>=0.10.0; extra == "mlx-lm"
Provides-Extra: dev
Requires-Dist: pytest>=7.0; extra == "dev"
Requires-Dist: ruff>=0.1.0; extra == "dev"
Dynamic: license-file
